holistic_anagram/__init__.py
holistic_anagram/english.txt
holistic_anagram/english_heroku.py
holistic_anagram/holistic_anagram.py
holistic_anagram-1.0.12.dist-info/LICENSE
holistic_anagram-1.0.12.dist-info/METADATA
holistic_anagram-1.0.12.dist-info/WHEEL
holistic_anagram-1.0.12.dist-info/top_level.txt
holistic_anagram-1.0.12.dist-info/RECORD
