Metadata-Version: 2.1
Name: holistic-anagram
Version: 1.0.12
Summary: A python package for anagrams
Home-page: https://github.com/MichaelQuant4R/holistic-anagram
Author: Michael S. Russell
Author-email: michael.r2014@yahoo.co.uk
License: MIT
Platform: UNKNOWN
Classifier: License :: OSI Approved :: MIT License
Classifier: Programming Language :: Python :: 3.0
Classifier: Programming Language :: Python :: 3.7
Classifier: Programming Language :: Python :: 3.8
Classifier: Programming Language :: Python :: 3.9
License-File: LICENSE
